Metadata-Version: 1.1
Name: tzupdate
Version: 2.0.0
Summary: Set the system timezone based on IP geolocation
Home-page: https://github.com/cdown/tzupdate
Author: Chris Down
Author-email: chris@chrisdown.name
License: Public Domain
Keywords: timezone localtime tz
Platform: UNKNOWN
Classifier: Development Status :: 5 - Production/Stable
Classifier: License :: Public Domain
Classifier: Operating System :: POSIX :: Linux
Classifier: Programming Language :: Python :: 3
Classifier: Programming Language :: Python :: 3.5
Classifier: Programming Language :: Python :: 3.6
Classifier: Programming Language :: Python :: 3.7
Classifier: Topic :: System
Classifier: Topic :: System :: Networking :: Time Synchronization
Classifier: Topic :: Utilities
